Metadata-Version: 2.4
Name: password-generator-vh
Version: 0.1.0
Summary: Simple and customizable password generator
Author: Victor Hugo
Requires-Python: >=3.7
Dynamic: author
Dynamic: requires-python
Dynamic: summary
